sosstat/__init__.py
sosstat/__main__.py
sosstat/bits.py
sosstat/collect/__init__.py
sosstat/collect/ip.py
sosstat/collect/irq.py
sosstat/collect/libvirt.py
sosstat/collect/ovs.py
sosstat/collect/pci.py
sosstat/collect/platform.py
sosstat/collect/software.py
sosstat/collect/topo.py
sosstat/collect/tuning.py
sosstat/output/__init__.py
sosstat/output/dot.py
sosstat/output/json.py
sosstat/output/text.py
sosstat-0.1.0.dist-info/METADATA
sosstat-0.1.0.dist-info/WHEEL
sosstat-0.1.0.dist-info/top_level.txt
sosstat-0.1.0.dist-info/RECORD
