Metadata-Version: 2.1
Name: sosstat
Version: 0.1.0
Summary: Information extractor from sos reports
Author-email: Veda Barrenkala <vbarrenk@redhat.com>, Robin Jarry <rjarry@redhat.com>
Requires-Python: >=3.6
Requires-Dist: graphviz
